setup.cfg
setup.py
wstunnel/__init__.py
wstunnel/client.py
wstunnel/exception.py
wstunnel/factory.py
wstunnel/filters.py
wstunnel/server.py
wstunnel/toolbox.py
wstunnel.egg-info/PKG-INFO
wstunnel.egg-info/SOURCES.txt
wstunnel.egg-info/dependency_links.txt
wstunnel.egg-info/entry_points.txt
wstunnel.egg-info/requires.txt
wstunnel.egg-info/top_level.txt
wstunnel/daemon/__init__.py
wstunnel/daemon/wstuncltd.py
wstunnel/daemon/wstunsrvd.py
wstunnel/svc/__init__.py
wstunnel/svc/registry.py
wstunnel/svc/wstuncltd.py
wstunnel/svc/wstunsrvd.py
wstunnel/test/__init__.py
wstunnel/test/test_daemon.py
wstunnel/test/test_toolbox.py
wstunnel/test/test_wstunnel.py