Metadata-Version: 1.1
Name: wstunnel
Version: 0.0.4
Summary: A Python WebSocket Tunnel
Home-page: https://github.com/ffalcinelli/wstunnel
Author: Fabio Falcinelli
Author-email: fabio.falcinelli@gmail.com
License: UNKNOWN
Download-URL: https://github.com/ffalcinelli/wstunnel/tarball/0.0.4
Keywords: tunneling,websocket,ssl
Platform: UNKNOWN
Classifier: Development Status :: 2 - Pre-Alpha
Classifier: Intended Audience :: Developers
Classifier: Intended Audience :: System Administrators
Classifier: Intended Audience :: Telecommunications Industry
Classifier: License :: OSI Approved :: GNU Lesser General Public License v3 or later (LGPLv3+)
Classifier: Programming Language :: Python
Classifier: Programming Language :: Python :: 2.7
Classifier: Programming Language :: Python :: 3.3
Classifier: Programming Language :: Python :: 3.4
Classifier: Topic :: Software Development :: Libraries :: Python Modules
Classifier: Topic :: Utilities
